tehilliday/__init__.py
tehilliday/tehillim.py
TehilliDay-0.1.0.dist-info/METADATA
TehilliDay-0.1.0.dist-info/WHEEL
TehilliDay-0.1.0.dist-info/top_level.txt
TehilliDay-0.1.0.dist-info/RECORD
