Metadata-Version: 2.1
Name: TehilliDay
Version: 0.1.0
Summary: A library to fetch daily Tehillim (Psalms)
Classifier: Programming Language :: Python :: 3
Classifier: License :: OSI Approved :: MIT License
Classifier: Operating System :: OS Independent
Requires-Python: >=3.6
Requires-Dist: requests
